pycontractions/__init__.py
pycontractions/contractions.py
pycontractions-2.0.1.dist-info/LICENSE
pycontractions-2.0.1.dist-info/METADATA
pycontractions-2.0.1.dist-info/WHEEL
pycontractions-2.0.1.dist-info/top_level.txt
pycontractions-2.0.1.dist-info/RECORD
