Metadata-Version: 2.1
Name: pycontractions
Version: 2.0.1
Summary: Intelligently expand and create contractions in text leveraging grammar checking and Word Mover's Distance.
Home-page: https://github.com/ian-beaver/pycontractions
Author: Ian Beaver, Next IT Corp
Author-email: ibeaver@nextit.com
License: BSD
Platform: UNKNOWN
Classifier: Development Status :: 5 - Production/Stable
Classifier: Environment :: Console
Classifier: Intended Audience :: Developers
Classifier: Intended Audience :: Science/Research
Classifier: Intended Audience :: Education
Classifier: License :: OSI Approved :: BSD License
Classifier: Operating System :: OS Independent
Classifier: Natural Language :: English
Classifier: Programming Language :: Python :: 2.7
Classifier: Programming Language :: Python :: 3
Classifier: Programming Language :: Python :: 3.4
Classifier: Programming Language :: Python :: 3.5
Classifier: Programming Language :: Python :: 3.6
Classifier: Topic :: Scientific/Engineering
Classifier: Topic :: Utilities
Classifier: Topic :: Text Processing
Classifier: Topic :: Text Processing :: Linguistic
Classifier: Topic :: Software Development :: Libraries
Requires-Dist: gensim (>=2.0)
Requires-Dist: language-check (>=1.0)
Requires-Dist: pyemd (>=0.4.4)
